fastgen/__init__.py
fastgen/__main__.py
fastgen/apps/__init__.py
fastgen/apps/generator_app.py
fastgen/blocks/__init__.py
fastgen/blocks/docker_blocks.py
fastgen/blocks/env_blocks.py
fastgen/blocks/main_blocks.py
fastgen/blocks/pydantic_blocks.py
fastgen/constants/__init__.py
fastgen/constants/path_constants.py
fastgen/enums/generator_enums.py
fastgen/enums/manager_enums.py
fastgen/exceptions/generator_exceptions.py
fastgen/generators/__init__.py
fastgen/generators/base_generator.py
fastgen/generators/model_generator.py
fastgen/generators/router_generator.py
fastgen/generators/schema_generator.py
fastgen/main.py
fastgen/managers/__init__.py
fastgen/managers/base_manager.py
fastgen/managers/pip_manager.py
fastgen/managers/poetry_manager.py
fastgen-0.3.5.dist-info/entry_points.txt
fastgen-0.3.5.dist-info/METADATA
fastgen-0.3.5.dist-info/LICENSE
fastgen-0.3.5.dist-info/WHEEL
fastgen-0.3.5.dist-info/RECORD
