Metadata-Version: 2.1
Name: fastgen
Version: 0.3.5
Summary: A CLI for your next FastAPI project
Home-page: https://github.com/kareemmahlees/fastgen
License: MIT
Keywords: CLI,python,typer,fastapi,fastgen,project,template,pip,poetry
Author: kareem
Author-email: kareemmahlees@gmail.com
Requires-Python: >=3.7,<4.0
Classifier: License :: OSI Approved :: MIT License
Classifier: Programming Language :: Python :: 3
Classifier: Programming Language :: Python :: 3.7
Classifier: Programming Language :: Python :: 3.8
Classifier: Programming Language :: Python :: 3.9
Classifier: Programming Language :: Python :: 3.10
Classifier: Programming Language :: Python :: 3.11
Requires-Dist: click (==8.1.3)
Requires-Dist: rich (>=12.5.1,<13.0.0)
Requires-Dist: typer[all] (>=0.6.1,<0.7.0)
Project-URL: Repository, https://github.com/kareemmahlees/fastgen
